azure_resource_graph/__init__.py
azure_resource_graph/client.py
azure_resource_graph/container_workload_analysis.py
azure_resource_graph/iam_analysis.py
azure_resource_graph/network_analysis.py
azure_resource_graph/storage_analysis.py
azure_resource_graph/vm_governance.py
azure_resource_graph/models/__init__.py
azure_resource_graph/models/comprehensive.py
azure_resource_graph/models/network_analysis.py
azure_resource_graph/models/storage_analysis.py
azure_resource_graph/models/vm_governance.py
azure_resource_graph-1.0.18.dist-info/licenses/LICENSE
azure_resource_graph-1.0.18.dist-info/METADATA
azure_resource_graph-1.0.18.dist-info/WHEEL
azure_resource_graph-1.0.18.dist-info/top_level.txt
azure_resource_graph-1.0.18.dist-info/RECORD
