Metadata-Version: 2.4
Name: azure-resource-graph
Version: 1.0.18
Summary: Python client for Azure Resource Graph API with storage encryption analysis
Home-page: https://github.com/hasura/azure-resource-graph
Author: Azure Resource Graph
Author-email: Azure Resource Graph <your.email@domain.com>
Maintainer-email: Azure Resource Graph <your.email@domain.com>
License: MIT
Project-URL: Homepage, https://github.com/yourusername/azure-resource-graph
Project-URL: Documentation, https://github.com/yourusername/azure-resource-graph/blob/main/README.md
Project-URL: Repository, https://github.com/yourusername/azure-resource-graph
Project-URL: Bug Tracker, https://github.com/yourusername/azure-resource-graph/issues
Project-URL: Changelog, https://github.com/yourusername/azure-resource-graph/blob/main/CHANGELOG.md
Keywords: azure,resource-graph,cloud,security,encryption,compliance,api-client,kusto,kql
Platform: any
Classifier: Development Status :: 4 - Beta
Classifier: Intended Audience :: Developers
Classifier: Intended Audience :: System Administrators
Classifier: License :: OSI Approved :: MIT License
Classifier: Operating System :: OS Independent
Classifier: Programming Language :: Python :: 3
Classifier: Programming Language :: Python :: 3.8
Classifier: Programming Language :: Python :: 3.9
Classifier: Programming Language :: Python :: 3.10
Classifier: Programming Language :: Python :: 3.11
Classifier: Programming Language :: Python :: 3.12
Classifier: Topic :: Software Development :: Libraries :: Python Modules
Classifier: Topic :: System :: Systems Administration
Classifier: Topic :: Security
Classifier: Topic :: Internet :: WWW/HTTP :: Dynamic Content
Requires-Python: >=3.8
License-File: LICENSE
Requires-Dist: requests<3.0.0,>=2.28.0
Requires-Dist: python-dotenv<2.0.0,>=0.19.0
Provides-Extra: auth
Requires-Dist: azure-identity<2.0.0,>=1.12.0; extra == "auth"
Requires-Dist: azure-cli-core<3.0.0,>=2.40.0; extra == "auth"
Provides-Extra: dev
Requires-Dist: pytest<8.0.0,>=7.0.0; extra == "dev"
Requires-Dist: pytest-cov<5.0.0,>=4.0.0; extra == "dev"
Requires-Dist: black<24.0.0,>=22.0.0; extra == "dev"
Requires-Dist: flake8<7.0.0,>=5.0.0; extra == "dev"
Requires-Dist: mypy<2.0.0,>=1.0.0; extra == "dev"
Provides-Extra: docs
Requires-Dist: sphinx<7.0.0,>=5.0.0; extra == "docs"
Requires-Dist: sphinx-rtd-theme<2.0.0,>=1.0.0; extra == "docs"
Provides-Extra: all
Requires-Dist: azure-identity<2.0.0,>=1.12.0; extra == "all"
Requires-Dist: azure-cli-core<3.0.0,>=2.40.0; extra == "all"
Requires-Dist: pytest<8.0.0,>=7.0.0; extra == "all"
Requires-Dist: pytest-cov<5.0.0,>=4.0.0; extra == "all"
Requires-Dist: black<24.0.0,>=22.0.0; extra == "all"
Requires-Dist: flake8<7.0.0,>=5.0.0; extra == "all"
Requires-Dist: mypy<2.0.0,>=1.0.0; extra == "all"
Requires-Dist: sphinx<7.0.0,>=5.0.0; extra == "all"
Requires-Dist: sphinx-rtd-theme<2.0.0,>=1.0.0; extra == "all"
Dynamic: author
Dynamic: home-page
Dynamic: license-file
Dynamic: platform
Dynamic: requires-python
